denonavr_cli/__init__.py
denonavr_cli/__main__.py
denonavr_cli-4.dist-info/entry_points.txt
denonavr_cli-4.dist-info/licenses/COPYING
denonavr_cli-4.dist-info/WHEEL
denonavr_cli-4.dist-info/METADATA
denonavr_cli-4.dist-info/RECORD
