Metadata-Version: 2.4
Name: denonavr_cli
Version: 4
Summary: A simple CLI for Denon AV receivers
Author-email: Michał Górny <mgorny@gentoo.org>
Requires-Python: >=3.9
Classifier: Development Status :: 5 - Production/Stable
Classifier: Environment :: Console
Classifier: License :: OSI Approved :: GNU General Public License v2 or later (GPLv2+)
Classifier: Programming Language :: Python :: 3 :: Only
License-File: COPYING
Requires-Dist: denonavr
Requires-Dist: ipython ; extra == "ipython-shell"
Requires-Dist: nest_asyncio ; extra == "ipython-shell"
Requires-Dist: pytest ; extra == "test"
Requires-Dist: pytest-asyncio ; extra == "test"
Project-URL: Homepage, https://github.com/mgorny/denonavr-cli/
Provides-Extra: ipython-shell
Provides-Extra: test
